Workbook

Sheet README
A1: Paytitude · Paytm UPI Growth Challenge, Track B · Round 2 annexure
A2: Settle & Pay: making Paytm the place merchants spend the money they see arrive · 9 October 2026
A4: Purpose | B4: Supporting evidence and the live model behind Paytitude_R2.pdf. Every number in the deck traces to a cell here or to a cited source (sheet 'Sources').
A6: Evidence-status legend
A7: Fact (cited) | B7: Public, sourced fact; see 'Sources' for URL and verification status
A8: Synthetic hypothesis | B8: Derived from the 50-row synthetic VOC dataset; for hypothesis stress-testing only, not market prevalence
A9: Projection | B9: Model output from stated assumptions; a projection, not a forecast or commitment
A10: To validate | B10: Open item to be measured (validation test, Paytm data or pilot)
A11: Validated (n = __) | B11: Measured with real target users; n stated. None yet: see 'Validation_Log'
A13: Synthetic-data disclosure | B13: Verbatim from the VOC workbook's 'Methodology Notes' sheet:
B14: This is synthetic research for hypothesis stress-testing, not customer evidence.
B15: The set intentionally includes positive, ambiguous and negative cases.
B16: Paytm collection usage, settlement timing, payment account, app choice and willingness to switch are not perfectly correlated.
B17: Business Pay is tested against alternative explanations: habit, staff control, accounting, verification, supplier rail and trust.
B18: Credit is deliberately not positioned as the default solution.
A20: Cell colour convention
A21: Blue text | B21: Hard-coded input or scenario lever
A22: Black text | B22: Formula
A23: Green text | B23: Link to another sheet
A24: Yellow fill | B24: Key assumption, or a cell to fill in
A26: File map
A27: Paytitude_R2.pdf | B27: Submission deck: cover, 15 content slides, annexure divider, annexures A1–A8
A28: Paytitude_R2.pptx | B28: Live version with animations and speaker notes (Morph renders in PowerPoint 2019/365)
A29: Paytitude_R2_Annexure.xlsx | B29: This workbook
A31: Sheets
A32: VOC_Synthetic | B32: All 50 rows of the synthetic VOC dataset, plus derived settlement profile, quadrant, group and contradiction flag
A33: VOC_Real | B33: Genuine exploratory conversations (notes to be added)
A34: Validation_Log | B34: One row per tested user (≥20). Summary formulas on top. EMPTY until the test is run
A35: Segment_Rules | B35: Inclusion rules and group counts, computed live from VOC_Synthetic
A36: Funnel_Model | B36: Cautious / base / upside funnel (projection)
A37: Share_Metric | B37: Main metric: Paytm share of segment vendor-UPI value
A38: Unit_Costs | B38: Cost per incremental MTU and per ₹ of incremental GMV, with and without build
A39: Sensitivity | B39: Halving the three key assumptions, plus the gap-days-only floor
A40: Pilot_Design | B40: 90-day randomised pilot
A41: Dependencies_Risks | B41: Dependency register and risk register
A42: Sources | B42: Every external source with URL, access date and verification status
A43: Change_Log_R1_R2 | B43: What changed since Round 1 and why

Sheet VOC_Synthetic
A1: SYNTHETIC: hypothesis stress-testing, not field research. Counts are not market shares; verbatims are dataset responses, not interviewed merchants.
A2: Source: Paytm_Track_B_VOCs.xlsx, sheet '50 VOCs' (columns A–Z unchanged). Columns AA–AD added by Paytitude.
A3: Respondent ID | B3: City | C3: Business Type | D3: Business Size | E3: Monthly Business Payment Estimate | F3: Main Business Payment Types | G3: Supplier Payment Frequency | H3: UPI Vendor Payment Frequency | I3: Current App Used for Business UPI | J3: Secondary App | K3: Paytm Collection Usage | L3: Paytm Outgoing Usage | M3: Who Makes Payments | N3: Who Chooses App | O3: Planned vs Urgent vs Routine UPI | P3: Supplier Credit | Q3: Cash-flow Pain | R3: Why Current App Is Preferred | S3: Reaction to Paytm Business Pay | T3: Would Switch to Paytm? | U3: Would Use Without Credit? | V3: Credit Need | W3: Key Pain Point | X3: Key Insight | Y3: Verbatim 1 | Z3: Verbatim 2 | AA3: Settlement profile (derived) | AB3: Segment quadrant | AC3: Segment group | AD3: Contradiction flag
A4: V01 | B4: Mumbai | C4: Hardware retailer | D4: Small | E4: ₹2–4 lakh | F4: UPI for small supplier payments; bank/cash for larger or formal dues | G4: 2–3 times/week | H4: Daily | I4: Google Pay | J4: PhonePe | K4: Paytm QR; settlement same day | L4: Rarely | M4: Owner + spouse | N4: Owner | O4: Routine | P4: Cash / same day | Q4: Low | R4: Same-day settlement | S4: Calls it another wallet/app without a clear advantage | T4: No | U4: Yes | V4: Low | W4: No meaningful switching benefit | X4: Daily UPI usage does not automatically create Business Pay demand. | Y4: Same steps hain toh app kyun badlu? | Z4: A better button is not enough to make me change apps. | AA4: Same day | AB4: Same-day + no friction | AC4: Group 3 | AD4: N
A5: V02 | B5: Mumbai | C5: Stationery wholesaler | D5: Small | E5: ₹1–2 lakh | F5: UPI for small vendor payments; bank transfer for larger dues | G5: Weekly | H5: 3–5 times/week | I5: Google Pay | J5: None | K5: Paytm QR; next day | L5: Never | M5: Owner | N5: Owner | O5: Routine | P5: Cash / 2–3 days | Q5: Low | R5: Muscle memory | S5: Would not switch for convenience alone | T5: Maybe | U5: Yes | V5: Low | W5: Habit | X5: Product parity is unlikely to overcome an established payment routine. | Y5: Market mein sab isi pe hain. | Z5: If it is the same number of steps, I will keep what I already use. | AA5: Next day | AB5: Next-day/separate + no friction | AC5: Group 2 | AD5: N
A6: V03 | B6: Bhopal | C6: Restaurant | D6: Small | E6: ₹2–4 lakh | F6: UPI for small supplier payments; bank/cash for larger or formal dues | G6: Daily | H6: Daily | I6: PhonePe | J6: Bank app | K6: Paytm QR; settlement same day | L6: Never | M6: Owner + spouse | N6: Owner | O6: Routine | P6: 15 days | Q6: Low | R6: Same-day settlement | S6: Rejects; same-day settlement already removes the proposed pain | T6: No | U6: Maybe | V6: Low | W6: No timing problem | X6: Daily UPI usage does not automatically create Business Pay demand. | Y6: Same steps hain toh app kyun badlu? | Z6: I already have a working payment habit. | AA6: Same day | AB6: Same-day + no friction | AC6: Group 3 | AD6: N
A7: V04 | B7: Mumbai | C7: Dairy retailer | D7: Small | E7: ₹4–7 lakh | F7: UPI for small vendor payments; bank transfer for larger dues | G7: Daily | H7: 2–3 times/week | I7: PhonePe | J7: Google Pay | K7: Paytm QR; next day | L7: Never | M7: Owner | N7: Owner | O7: Routine | P7: 30 days | Q7: Low | R7: Local market uses the app | S7: Would try for a few payments but keep the existing app | T7: Maybe | U7: Yes | V7: Low | W7: No differentiated benefit | X7: Product parity is unlikely to overcome an established payment routine. | Y7: Market mein sab isi pe hain. | Z7: If it is the same number of steps, I will keep what I already use. | AA7: Next day | AB7: Next-day/separate + no friction | AC7: Group 2 | AD7: N
A8: V05 | B8: Mohali | C8: Salon | D8: Small | E8: ₹80k–₹1.5 lakh | F8: UPI for small vendor payments; bank transfer for larger dues | G8: 2–4 times/month | H8: Weekly | I8: PhonePe | J8: Bank app | K8: Paytm QR; settlement same day | L8: Never | M8: Owner | N8: Owner | O8: Routine | P8: 30 days | Q8: Low | R8: Habit and staff familiarity | S8: Only interested if it adds accounting/verification value | T8: Maybe | U8: Maybe | V8: Low | W8: No differentiated benefit | X8: Convenience alone is not enough to switch | Y8: PhonePe hi chalta hai, aadat ho gayi hai. | Z8: If it is the same number of steps, I will keep what I already use. | AA8: Same day | AB8: Same-day + no friction | AC8: Group 3 | AD8: N
A9: V06 | B9: Mumbai | C9: Mobile accessories retailer | D9: Small | E9: ₹2–5 lakh | F9: UPI for small supplier payments; bank/cash for larger or formal dues | G9: Weekly | H9: Daily | I9: PhonePe | J9: Bank app | K9: Paytm QR; settlement same day | L9: Never | M9: Owner | N9: Owner | O9: Routine + urgent | P9: 15 days | Q9: Low | R9: Habit; no current pain | S9: Rejects; same-day settlement already removes the proposed pain | T9: No | U9: Yes | V9: Low | W9: No meaningful switching benefit | X9: Daily UPI usage does not automatically create Business Pay demand. | Y9: Mera settlement same day aa jata hai, toh problem kya hai? | Z9: I already have a working payment habit. | AA9: Same day | AB9: Same-day + no friction | AC9: Group 3 | AD9: N
A10: V07 | B10: Nashik | C10: Electrical shop | D10: Small | E10: ₹1–3 lakh | F10: Daily/weekly UPI to suppliers; bank for rent, salaries or large invoices | G10: 2–4 times/month | H10: 3–5 times/week | I10: Google Pay | J10: Bank app | K10: Paytm QR; settlement next day | L10: Rarely | M10: Owner + spouse | N10: Owner | O10: Routine + urgent | P10: None / cash | Q10: Medium | R10: PhonePe is already open and suppliers use it | S10: Strong interest, but only if it removes the need to transfer money between accounts | T10: Maybe | U10: Yes | V10: Low | W10: Morning supplier payment before settlement | X10: The strongest Business Pay case is a real timing/account gap, not generic UPI convenience. | Y10: Subah supplier ko paisa chahiye, collection baad mein settle hota hai. | Z10: Loan nahi chahiye. Jo collect kiya hai, woh use karna hai. | AA10: Next day | AB10: Next-day/separate + friction | AC10: Group 1 | AD10: N
A11: V08 | B11: Mumbai | C11: Beauty products distributor | D11: Small | E11: ₹70k–₹1.2 lakh | F11: UPI for small vendor payments; bank transfer for larger dues | G11: Weekly | H11: 3–5 times/week | I11: Google Pay | J11: Bank app | K11: Paytm QR; next day | L11: Rarely | M11: Owner | N11: Owner | O11: Routine | P11: 15 days | Q11: Low | R11: Local market uses the app | S11: Would not switch for convenience alone | T11: Maybe | U11: Yes | V11: Low | W11: Habit | X11: Habit is a real barrier when there is no concrete pain. | Y11: Mujhe naya system seekhne ka reason nahi dikhta. | Z11: If it is the same number of steps, I will keep what I already use. | AA11: Next day | AB11: Next-day/separate + no friction | AC11: Group 2 | AD11: N
A12: V09 | B12: Jaipur | C12: Hardware retailer | D12: Small | E12: ₹2–4 lakh | F12: Daily/weekly UPI to suppliers; bank for rent, salaries or large invoices | G12: 2–4 times/month | H12: Daily | I12: Google Pay | J12: PhonePe | K12: Paytm QR; settlement next day | L12: Sometimes | M12: Owner | N12: Owner | O12: Routine + urgent | P12: 2–7 days | Q12: Low | R12: Supplier sends QR on WhatsApp | S12: Strong interest, but only if it removes the need to transfer money between accounts | T12: Yes | U12: Maybe | V12: Medium | W12: Money arrives in a different account | X12: The strongest Business Pay case is a real timing/account gap, not generic UPI convenience. | Y12: Aaj ka maal aaj lena hai; kal ka settlement ka wait nahi kar sakta. | Z12: Loan nahi chahiye. Jo collect kiya hai, woh use karna hai. | AA12: Next day | AB12: Next-day/separate + friction | AC12: Group 1 | AD12: N
A13: V10 | B13: Nagpur | C13: Dairy distributor | D13: Small | E13: ₹12–20 lakh | F13: Daily/weekly UPI to suppliers; bank for rent, salaries or large invoices | G13: Daily | H13: 4–6 times/week | I13: PhonePe | J13: Bank app | K13: Paytm QR; settlement same day | L13: Sometimes | M13: Owner + brother | N13: Owner | O13: Urgent | P13: 7 days | Q13: High | R13: Fast for small payments | S13: Useful for morning/urgent purchases; not enough to replace the existing app everywhere | T13: Maybe | U13: Yes | V13: Medium | W13: Stock payment due before collections settle | X13: Daily-supply merchants can have repeated but narrow payment-timing friction. | Y13: Account alag hai, pehle transfer karna padta hai. | Z13: Urgent payment ke time app change nahi, direct flow chahiye. | AA13: Same day | AB13: Same-day + friction | AC13: Group 2 | AD13: Y
A14: V11 | B14: Mumbai | C14: Furniture retailer | D14: Medium | E14: ₹7–12 lakh | F14: Daily/weekly UPI to suppliers; bank for rent, salaries or large invoices | G14: 2–3 times/week | H14: Daily | I14: Bank app | J14: Bank app | K14: Paytm QR; same-day settlement to current account | L14: Never | M14: Owner | N14: Owner | O14: Routine | P14: 7 days | Q14: Low | R14: Invoices, approvals and bank records | S14: Useful for morning/urgent purchases; not enough to replace the existing app everywhere | T14: No | U14: Yes | V14: Low | W14: Money arrives in a different account | X14: Formal supplier payments stay outside the UPI-app wedge | Y14: Subah supplier ko paisa chahiye, collection baad mein settle hota hai. | Z14: Loan nahi chahiye. Jo collect kiya hai, woh use karna hai. | AA14: Same day | AB14: Same-day + friction | AC14: Group 2 | AD14: Y
... A53: V50 | B53: Gurugram | C53: Pharmacy | D53: Small | E53: ₹1–3 lakh | F53: Daily/weekly UPI to suppliers; bank for rent, salaries or large invoices | G53: 2–4 times/month | H53: 3–5 times/week | I53: PhonePe | J53: Google Pay | K53: Paytm QR; settlement next day | L53: Sometimes | M53: Owner | N53: Owner | O53: Routine + urgent | P53: 3 days | Q53: High | R53: Fast for small payments | S53: Would use for daily supplier payments if today's collections can be used before settlement | T53: Yes | U53: Maybe | V53: Low | W53: Stock payment due before collections settle | X53: The strongest Business Pay case is a real timing/account gap, not generic UPI convenience. | Y53: Aaj ka maal aaj lena hai; kal ka settlement ka wait nahi kar sakta. | Z53: If I can pay directly from today's collection, that saves an actual step. | AA53: Next day | AB53: Next-day/separate + friction | AC53: Group 1 | AD53: N

Sheet VOC_Real
A1: Genuine exploratory merchant conversations
A2: GENUINE, EXPLORATORY, SMALL SAMPLE. Business types as reported by the team; notes and verbatims not yet supplied to the build. Do not treat as validation (that is Validation_Log).
A4: # | B4: Date | C4: Business type | D4: City | E4: Key points | F4: Verbatim (original language) | G4: Status
A5: 1 | C5: Pharmacy | E5: [notes to be added by team] | F5: [verbatim to be added] | G5: Reported; notes pending
A6: 2 | C6: Café | E6: [notes to be added by team] | F6: [verbatim to be added] | G6: Reported; notes pending
A7: 3 | C7: FMCG retailer | E7: [notes to be added by team] | F7: [verbatim to be added] | G7: Reported; notes pending
A8: 4 | C8: Tractor dealer | E8: [notes to be added by team] | F8: [verbatim to be added] | G8: Reported; notes pending
A9: 5 | C9: Merchant who pays vendors by UPI routinely | E9: [notes to be added by team] | F9: [verbatim to be added] | G9: Reported; notes pending

Sheet Validation_Log
A1: Solution validation log (≥20 target users)
A2: EMPTY: no validation data has been supplied. Fill one row per tested merchant from row 19; summary recalculates; then run fill_validation.py to update slide 10 and re-export the PDF.
A4: Merchants tested (n) | E4: =COUNTA($A$19:$A$78) -> 0
A5: Meets the ≥20 requirement? | E5: =IF($E$4>=20,"Yes","No: "&(20-$E$4)&" more needed") -> No: 20 more needed
A6: Completed the prototype task unaided | E6: =IFERROR(COUNTIF($J$19:$J$78,"Y")/$E$4,"—") -> —
A7: Named a supplier payment they would move | E7: =IFERROR(COUNTIF($L$19:$L$78,"Y")/$E$4,"—") -> —
A8: Agreed to a follow-up trial | E8: =IFERROR(COUNTIF($M$19:$M$78,"Y")/$E$4,"—") -> —
A9: Enabled instant settlement in session | E9: =IFERROR(COUNTIF($N$19:$N$78,"Y")/$E$4,"—") -> —
A10: Made at least one commitment | E10: =IFERROR(SUMPRODUCT(--((($L$19:$L$78="Y")+($M$19:$M$78="Y")+($N$19:$N$78="Y"))>0))/$E$4,"—") -> —
A11: Used instant settlement in last 30 days | E11: =IFERROR(COUNTIF($O$19:$O$78,"Y")/$E$4,"—") -> —
A12: Settlement: same day / next day / separate account | E12: =COUNTIF($F$19:$F$78,"Same day")&" / "&COUNTIF($F$19:$F$78,"Next day")&" / "&COUNTIF($F$19:$F$78,"Separate account") -> 0 / 0 / 0
A13: Average of last 5 payments they would move | E13: =IFERROR(AVERAGE($S$19:$S$78),"—") -> —
A14: Share of answers observed (not stated) | E14: =IFERROR(COUNTIF($R$19:$R$78,"Observed")/COUNTA($R$19:$R$78),"—") -> —
A15: Top objection counts: Trust / Habit / Supplier / Staff / Account / Other | E15: =COUNTIF($P$19:$P$78,"Trust")&" / "&COUNTIF($P$19:$P$78,"Habit")&" / "&COUNTIF($P$19:$P$78,"Supplier")&" / "&COUNTIF($P$19:$P$78,"Staff")&" / "&COUNTIF($P$19:$P$78,"Account set-up")&" / "&COUNTIF($P$19:$P$78,"Other") -> 0 / 0 / 0 / 0 / 0 / 0
A17: EXAMPLE (not data) | B17: 12 Oct 2026 | C17: Pune | D17: Hardware retailer | E17: Y | F17: Next day | G17: 5 | H17: PhonePe | I17: Prototype walkthrough | J17: Y | K17: Will pay Monday's cable order via Settle & Pay | L17: Y | M17: Y | N17: N | O17: N | P17: Habit | Q17: Agar collection se seedha jaata hai toh theek hai | R17: Observed | S17: 2
A18: ID | B18: Date | C18: City | D18: Business type | E18: Paytm collector (Y/N) | F18: Settlement profile (Same day / Next day / Separate account) | G18: Vendor UPI payments per week | H18: Current app | I18: Method (Concept test / Prototype walkthrough / Real-world trial) | J18: Task completed unaided (Y/N) | K18: Commitment made (text) | L18: Named a supplier payment to move (Y/N) | M18: Agreed to follow-up trial (Y/N) | N18: Enabled instant settlement in session (Y/N) | O18: Used instant settlement in last 30 days (Y/N) | P18: Top objection (Trust / Habit / Supplier / Staff / Account set-up / Other) | Q18: Verbatim | R18: Evidence type (Observed / Stated) | S18: Of last 5 payments, would move (0–5)

Sheet Segment_Rules
A1: Segment rules and group counts (synthetic hypothesis)
A2: All counts are COUNTIFS over VOC_Synthetic. SYNTHETIC: illustrates the hypothesis, not market prevalence.
A4: Group 1 inclusion rules (all must hold)
A5: 1. Regular Paytm collector (Paytm QR or Soundbox)
A6: 2. Next-day settlement, or settlement into a separate current account
A7: 3. Pays vendors by UPI at least weekly
A8: 4. Payment app chosen by owner or manager
A9: 5. States a timing, transfer or staff-control friction
A11: Group | B11: Rule | C11: Merchants | D11: Yes | E11: Maybe | F11: No | G11: Rows
A12: Group 1 | B12: High potential: all five rules | C12: =COUNTIF(VOC_Synthetic!$AC$4:$AC$53,A12) -> 16 | D12: =COUNTIFS(VOC_Synthetic!$AC$4:$AC$53,$A12,VOC_Synthetic!$T$4:$T$53,"Yes") -> 7 | E12: =COUNTIFS(VOC_Synthetic!$AC$4:$AC$53,$A12,VOC_Synthetic!$T$4:$T$53,"Maybe") -> 9 | F12: =COUNTIFS(VOC_Synthetic!$AC$4:$AC$53,$A12,VOC_Synthetic!$T$4:$T$53,"No") -> 0 | G12: V07 V09 V14 V16 V20 V24 V25 V29 V32 V33 V43 V44 V45 V47 V49 V50
A13: Group 2 | B13: Paytm collector not in Group 1 or 3: next-day with no friction (7) or same-day with a friction (9, of which 7 contradictory) | C13: =COUNTIF(VOC_Synthetic!$AC$4:$AC$53,A13) -> 16 | D13: =COUNTIFS(VOC_Synthetic!$AC$4:$AC$53,$A13,VOC_Synthetic!$T$4:$T$53,"Yes") -> 4 | E13: =COUNTIFS(VOC_Synthetic!$AC$4:$AC$53,$A13,VOC_Synthetic!$T$4:$T$53,"Maybe") -> 8 | F13: =COUNTIFS(VOC_Synthetic!$AC$4:$AC$53,$A13,VOC_Synthetic!$T$4:$T$53,"No") -> 4 | G13: V02 V04 V08 V37 V38 V41 V46 V10 V11 V12 V17 V19 V21 V30 V35 V36
A14: Group 3 | B14: No or partial Paytm collection (8); accountant chooses app (2); same-day with no friction (8) | C14: =COUNTIF(VOC_Synthetic!$AC$4:$AC$53,A14) -> 18 | D14: =COUNTIFS(VOC_Synthetic!$AC$4:$AC$53,$A14,VOC_Synthetic!$T$4:$T$53,"Yes") -> 1 | E14: =COUNTIFS(VOC_Synthetic!$AC$4:$AC$53,$A14,VOC_Synthetic!$T$4:$T$53,"Maybe") -> 4 | F14: =COUNTIFS(VOC_Synthetic!$AC$4:$AC$53,$A14,VOC_Synthetic!$T$4:$T$53,"No") -> 13 | G14: All other rows
A15: Total | C15: =SUM(C12:C14) -> 50 | D15: =SUM(D12:D14) -> 12 | E15: =SUM(E12:E14) -> 21 | F15: =SUM(F12:F14) -> 17
A17: Settlement profile (Paytm collectors) | B17: Note | C17: Merchants | D17: Yes | E17: Maybe | F17: No
A18: Same day | C18: =COUNTIF(VOC_Synthetic!$AA$4:$AA$53,A18) -> 19 | D18: =COUNTIFS(VOC_Synthetic!$AA$4:$AA$53,$A18,VOC_Synthetic!$T$4:$T$53,"Yes") -> 4 | E18: =COUNTIFS(VOC_Synthetic!$AA$4:$AA$53,$A18,VOC_Synthetic!$T$4:$T$53,"Maybe") -> 6 | F18: =COUNTIFS(VOC_Synthetic!$AA$4:$AA$53,$A18,VOC_Synthetic!$T$4:$T$53,"No") -> 9
A19: Next day | C19: =COUNTIF(VOC_Synthetic!$AA$4:$AA$53,A19) -> 17 | D19: =COUNTIFS(VOC_Synthetic!$AA$4:$AA$53,$A19,VOC_Synthetic!$T$4:$T$53,"Yes") -> 4 | E19: =COUNTIFS(VOC_Synthetic!$AA$4:$AA$53,$A19,VOC_Synthetic!$T$4:$T$53,"Maybe") -> 11 | F19: =COUNTIFS(VOC_Synthetic!$AA$4:$AA$53,$A19,VOC_Synthetic!$T$4:$T$53,"No") -> 2
A20: Next day, separate account | C20: =COUNTIF(VOC_Synthetic!$AA$4:$AA$53,A20) -> 6 | D20: =COUNTIFS(VOC_Synthetic!$AA$4:$AA$53,$A20,VOC_Synthetic!$T$4:$T$53,"Yes") -> 3 | E20: =COUNTIFS(VOC_Synthetic!$AA$4:$AA$53,$A20,VOC_Synthetic!$T$4:$T$53,"Maybe") -> 3 | F20: =COUNTIFS(VOC_Synthetic!$AA$4:$AA$53,$A20,VOC_Synthetic!$T$4:$T$53,"No") -> 0
A21: Regular Paytm collectors | C21: =SUM(C18:C20) -> 42
A23: Model proxy | B23: Definition | C23: Value | G23: Status
A24: Next-day or separate-account merchants | B24: Next day + next day, separate account | C24: =C19+C20 -> 23 | G24: Synthetic hypothesis
A25: Settlement share | B25: Next-day or separate ÷ regular collectors (23 of 42) | C25: =C24/C21 -> 0.54761905 | G25: Synthetic hypothesis; replace with Paytm settlement data
A26: Group 1 merchants | B26: Next-day or separate with a stated friction | C26: =C12 -> 16 | G26: Synthetic hypothesis
A27: Friction share | B27: Group 1 ÷ next-day or separate (16 of 23) | C27: =C26/C24 -> 0.69565217 | G27: Synthetic hypothesis
A28: Group 1 yes | B28: Stated 'would switch: yes' | C28: =D12 -> 7 | G28: Synthetic hypothesis
A29: Group 1 maybe | B29: Stated 'would switch: maybe' | C29: =E12 -> 9 | G29: Synthetic hypothesis
A30: Group 1 never or rarely pay via Paytm | B30: Paytm outgoing usage = Never or Rarely | C30: =COUNTIFS(VOC_Synthetic!$AC$4:$AC$53,"Group 1",VOC_Synthetic!$L$4:$L$53,"Never")+COUNTIFS(VOC_Synthetic!$AC$4:$AC$53,"Group 1",VOC_Synthetic!$L$4:$L$53,"Rarely") -> 9 | G30: Synthetic hypothesis
A31: Not already a Paytm payer | B31: Never or rarely ÷ Group 1 (9 of 16) | C31: =C30/C26 -> 0.5625 | G31: Synthetic hypothesis
A32: Same-day merchants saying 'no' | B32: Of 19 same-day collectors | C32: =F18&" of "&C18 -> 9 of 19 | G32: Synthetic hypothesis
A33: Pay vendors by UPI at least 2–3 times a week | B33: Of 50 rows | C33: =COUNTA(VOC_Synthetic!$A$4:$A$53)-COUNTIF(VOC_Synthetic!$H$4:$H$53,"Weekly")-COUNTIF(VOC_Synthetic!$H$4:$H$53,"Rarely") -> 41 | G33: Synthetic hypothesis
A34: Contradictory rows | B34: Flagged V10, V11, V12, V17, V19, V23, V34, V35, V36, V40, V42 | C34: =COUNTIF(VOC_Synthetic!$AD$4:$AD$53,"Y") -> 11 | G34: Audit
A35: Contradictory rows inside Group 1 | B35: Group 1 is unaffected by the clean-sample sensitivity | C35: =COUNTIFS(VOC_Synthetic!$AC$4:$AC$53,"Group 1",VOC_Synthetic!$AD$4:$AD$53,"Y") -> 0 | G35: Audit
A37: 2×2 quadrant (slide 5) | B37: Rows | C37: Merchants | D37: Yes | E37: Maybe | F37: No
A38: Next-day/separate + friction | B38: V07 V09 V14 V16 V20 V24 V25 V29 V32 V33 V43 V44 V45 V47 V49 V50 | C38: =COUNTIF(VOC_Synthetic!$AB$4:$AB$53,A38) -> 16 | D38: =COUNTIFS(VOC_Synthetic!$AB$4:$AB$53,$A38,VOC_Synthetic!$T$4:$T$53,"Yes") -> 7 | E38: =COUNTIFS(VOC_Synthetic!$AB$4:$AB$53,$A38,VOC_Synthetic!$T$4:$T$53,"Maybe") -> 9 | F38: =COUNTIFS(VOC_Synthetic!$AB$4:$AB$53,$A38,VOC_Synthetic!$T$4:$T$53,"No") -> 0
A39: Next-day/separate + no friction | B39: V02 V04 V08 V37 V38 V41 V46 | C39: =COUNTIF(VOC_Synthetic!$AB$4:$AB$53,A39) -> 7 | D39: =COUNTIFS(VOC_Synthetic!$AB$4:$AB$53,$A39,VOC_Synthetic!$T$4:$T$53,"Yes") -> 0 | E39: =COUNTIFS(VOC_Synthetic!$AB$4:$AB$53,$A39,VOC_Synthetic!$T$4:$T$53,"Maybe") -> 5 | F39: =COUNTIFS(VOC_Synthetic!$AB$4:$AB$53,$A39,VOC_Synthetic!$T$4:$T$53,"No") -> 2
A40: Same-day + friction | B40: V10 V11 V12 V17 V19 V21 V30 V35 V36 | C40: =COUNTIF(VOC_Synthetic!$AB$4:$AB$53,A40) -> 9 | D40: =COUNTIFS(VOC_Synthetic!$AB$4:$AB$53,$A40,VOC_Synthetic!$T$4:$T$53,"Yes") -> 4 | E40: =COUNTIFS(VOC_Synthetic!$AB$4:$AB$53,$A40,VOC_Synthetic!$T$4:$T$53,"Maybe") -> 3 | F40: =COUNTIFS(VOC_Synthetic!$AB$4:$AB$53,$A40,VOC_Synthetic!$T$4:$T$53,"No") -> 2
A41: Same-day + no friction | B41: V01 V03 V05 V06 V22 V28 V34 V42 | C41: =COUNTIF(VOC_Synthetic!$AB$4:$AB$53,A41) -> 8 | D41: =COUNTIFS(VOC_Synthetic!$AB$4:$AB$53,$A41,VOC_Synthetic!$T$4:$T$53,"Yes") -> 0 | E41: =COUNTIFS(VOC_Synthetic!$AB$4:$AB$53,$A41,VOC_Synthetic!$T$4:$T$53,"Maybe") -> 2 | F41: =COUNTIFS(VOC_Synthetic!$AB$4:$AB$53,$A41,VOC_Synthetic!$T$4:$T$53,"No") -> 6
A42: Excluded: accountant chooses app | B42: V18 V27 | C42: =COUNTIF(VOC_Synthetic!$AB$4:$AB$53,A42) -> 2 | D42: =COUNTIFS(VOC_Synthetic!$AB$4:$AB$53,$A42,VOC_Synthetic!$T$4:$T$53,"Yes") -> 0 | E42: =COUNTIFS(VOC_Synthetic!$AB$4:$AB$53,$A42,VOC_Synthetic!$T$4:$T$53,"Maybe") -> 1 | F42: =COUNTIFS(VOC_Synthetic!$AB$4:$AB$53,$A42,VOC_Synthetic!$T$4:$T$53,"No") -> 1
A43: Excluded: no or partial Paytm collection | B43: V13 V15 V23 V26 V31 V39 V40 V48 | C43: =COUNTIF(VOC_Synthetic!$AB$4:$AB$53,A43) -> 8 | D43: =COUNTIFS(VOC_Synthetic!$AB$4:$AB$53,$A43,VOC_Synthetic!$T$4:$T$53,"Yes") -> 1 | E43: =COUNTIFS(VOC_Synthetic!$AB$4:$AB$53,$A43,VOC_Synthetic!$T$4:$T$53,"Maybe") -> 1 | F43: =COUNTIFS(VOC_Synthetic!$AB$4:$AB$53,$A43,VOC_Synthetic!$T$4:$T$53,"No") -> 6

Sheet Funnel_Model
A1: Incremental growth funnel: cautious / base / upside
A2: PROJECTION, NOT FORECAST. Run-rate at the end of year one. Every rate is an assumption or a synthetic proxy, to be replaced by Paytm data and pilot results.
A4: Driver | B4: Cautious | C4: Base | D4: Upside | E4: Source / status
A5: Paytm device merchants | B5: 15700000 | C5: 15700000 | D5: 15700000 | E5: Fact: Paytm Q1 FY27 release (S1)
A6: Share paying vendors by UPI at least weekly | B6: 0.35 | C6: 0.5 | D6: 0.6 | E6: Assumption (dataset pre-selected for UPI payers)
A7: Share settled next day or into a separate account | B7: =Segment_Rules!$C$25 -> 0.54761905 | C7: =Segment_Rules!$C$25 -> 0.54761905 | D7: =Segment_Rules!$C$25 -> 0.54761905 | E7: Synthetic proxy: 23 of 42 collectors; replace with Paytm settlement data
A8: Share with a stated friction | B8: =Segment_Rules!$C$27 -> 0.69565217 | C8: =Segment_Rules!$C$27 -> 0.69565217 | D8: =Segment_Rules!$C$27 -> 0.69565217 | E8: Synthetic proxy: 16 of 23
A9: Eligible merchants | B9: =B5*B6*B7*B8 -> 2093333.3 | C9: =C5*C6*C7*C8 -> 2990476.2 | D9: =D5*D6*D7*D8 -> 3588571.4 | E9: Result
A10: Share exposed in year one (field force + in-app) | B10: 0.25 | C10: 0.4 | D10: 0.55 | E10: Assumption
A11: Exposed merchants | B11: =B9*B10 -> 523333.33 | C11: =C9*C10 -> 1196190.5 | D11: =D9*D10 -> 1973714.3 | E11: Result
A12: Conversion of stated 'yes' | B12: 0.25 | C12: 0.4 | D12: 0.6 | E12: Assumption
A13: Conversion of stated 'maybe' | B13: 0.05 | C13: 0.1 | D13: 0.2 | E13: Assumption
A14: Group 1 'yes' count | B14: =Segment_Rules!$C$28 -> 7 | C14: =Segment_Rules!$C$28 -> 7 | D14: =Segment_Rules!$C$28 -> 7 | E14: Synthetic (7 of 16)
A15: Group 1 'maybe' count | B15: =Segment_Rules!$C$29 -> 9 | C15: =Segment_Rules!$C$29 -> 9 | D15: =Segment_Rules!$C$29 -> 9 | E15: Synthetic (9 of 16)
A16: Group 1 merchants | B16: =Segment_Rules!$C$26 -> 16 | C16: =Segment_Rules!$C$26 -> 16 | D16: =Segment_Rules!$C$26 -> 16 | E16: Synthetic
A17: First-time activation rate | B17: =(B12*B14+B13*B15)/B16 -> 0.1375 | C17: =(C12*C14+C13*C15)/C16 -> 0.23125 | D17: =(D12*D14+D13*D15)/D16 -> 0.375 | E17: Assumption applied to dataset propensity
A18: Activated merchants | B18: =B11*B17 -> 71958.333 | C18: =C11*C17 -> 276619.05 | D18: =D11*D17 -> 740142.86 | E18: Result
A19: Repeat rate (2+ payments in each of months 2 and 3) | B19: 0.35 | C19: 0.5 | D19: 0.65 | E19: Assumption
A20: Repeat merchants | B20: =B18*B19 -> 25185.417 | C20: =C18*C19 -> 138309.52 | D20: =D18*D19 -> 481092.86 | E20: Result
A21: Not already a Paytm payer | B21: =Segment_Rules!$C$31 -> 0.5625 | C21: =Segment_Rules!$C$31 -> 0.5625 | D21: =Segment_Rules!$C$31 -> 0.5625 | E21: Synthetic proxy: 9 of 16 Group 1 never or rarely pay via Paytm
A22: Incremental MTU | B22: =B20*B21 -> 14166.797 | C22: =C20*C21 -> 77799.107 | D22: =D20*D21 -> 270614.73 | E22: Result
A23: Weeks per month | B23: 4.3 | C23: 4.3 | D23: 4.3 | E23: Convention
A24: Vendor UPI payments per merchant per month | B24: =(2.5*B23+4*B23+5*B23+26)/4 -> 18.8625 | C24: =(2.5*C23+4*C23+5*C23+26)/4 -> 18.8625 | D24: =(2.5*D23+4*D23+5*D23+26)/4 -> 18.8625 | E24: Synthetic: midpoints of 2–3, 3–5, 4–6 a week and daily (26 a month), equally weighted
A25: Share of those payments shifted to Paytm | B25: 0.25 | C25: 0.4 | D25: 0.6 | E25: Assumption
A26: Incremental Paytm business payments a month | B26: =B20*B24*B25 -> 118764.98 | C26: =C20*C24*C25 -> 1043545.4 | D26: =D20*D24*D25 -> 5444768.4 | E26: Result
A27: Average vendor payment (₹) | B27: 2000 | C27: 2500 | D27: 3500 | E27: Assumption
A28: Baseline already on Paytm (share of shifted value) | B28: 0.15 | C28: 0.15 | D28: 0.15 | E28: Assumption. Occasional Paytm payers' shifted payments are assumed mostly new; verify in pilot
A29: Incremental business UPI GMV a month (₹) | B29: =B26*B27*(1-B28) -> 2.0190047e+08 | C29: =C26*C27*(1-C28) -> 2.2175339e+09 | D29: =D26*D27*(1-D28) -> 1.6198186e+10 | E29: Result
A30: Incremental GMV a month (₹ crore) | B30: =B29/10^7 -> 20.190047 | C30: =C29/10^7 -> 221.75339 | D30: =D29/10^7 -> 1619.8186 | E30: Result
A31: Annual run-rate (₹ crore) | B31: =B30*12 -> 242.28056 | C31: =C30*12 -> 2661.0407 | D31: =D30*12 -> 19437.823 | E31: Result: deck uses ≈₹240 / ≈₹2,660 / ≈₹19,400 crore (3 significant figures)
A32: Incremental MTU per 1,000 exposed | B32: =B22/B11*1000 -> 27.070312 | C32: =C22/C11*1000 -> 65.039062 | D32: =D22/D11*1000 -> 137.10938 | E32: Result

Sheet Share_Metric
A1: Main metric: increase in Paytm's share of segment UPI GMV
A2: PROJECTION. The segment pool is the addressable outgoing vendor-UPI value, NOT incremental Paytm GMV.
A4: Item | B4: Cautious | C4: Base | D4: Upside | E4: Formula / note
A5: Eligible merchants | B5: =Funnel_Model!B9 -> 2093333.3 | C5: =Funnel_Model!C9 -> 2990476.2 | D5: =Funnel_Model!D9 -> 3588571.4 | E5: Funnel_Model row 9
A6: Exposed merchants | B6: =Funnel_Model!B11 -> 523333.33 | C6: =Funnel_Model!C11 -> 1196190.5 | D6: =Funnel_Model!D11 -> 1973714.3 | E6: Funnel_Model row 11
A7: Vendor UPI payments per merchant per month | B7: =Funnel_Model!B24 -> 18.8625 | C7: =Funnel_Model!C24 -> 18.8625 | D7: =Funnel_Model!D24 -> 18.8625 | E7: Funnel_Model row 24
A8: Average vendor payment (₹) | B8: =Funnel_Model!B27 -> 2000 | C8: =Funnel_Model!C27 -> 2500 | D8: =Funnel_Model!D27 -> 3500 | E8: Funnel_Model row 27
A9: Segment pool a month (₹ crore) | B9: =B5*B7*B8/10^7 -> 7897.1 | C9: =C5*C7*C8/10^7 -> 14101.964 | D9: =D5*D7*D8/10^7 -> 23691.3 | E9: Eligible × payments × ticket: addressable, not incremental
A10: Segment pool a year (₹ lakh crore) | B10: =B9*12/10^5 -> 0.947652 | C10: =C9*12/10^5 -> 1.6922357 | D10: =D9*12/10^5 -> 2.842956 | E10: × 12
A11: Exposed-cohort pool a month (₹ crore) | B11: =B6*B7*B8/10^7 -> 1974.275 | C11: =C6*C7*C8/10^7 -> 5640.7857 | D11: =D6*D7*D8/10^7 -> 13030.215 | E11: Exposed × payments × ticket
A12: Incremental Paytm GMV a month (₹ crore) | B12: =Funnel_Model!B30 -> 20.190047 | C12: =Funnel_Model!C30 -> 221.75339 | D12: =Funnel_Model!D30 -> 1619.8186 | E12: Funnel_Model row 30
A13: Share increase across exposed cohort (pts) | B13: =B12/B11*100 -> 1.0226563 | C13: =C12/C11*100 -> 3.93125 | D13: =D12/D11*100 -> 12.43125 | E13: Incremental ÷ exposed pool
A14: Share increase across whole eligible segment (pts) | B14: =B12/B9*100 -> 0.25566406 | C14: =C12/C9*100 -> 1.5725 | D14: =D12/D9*100 -> 6.8371875 | E14: Incremental ÷ segment pool, end of year one
A15: Expected intention-to-treat lift in pilot (pts, before overlap) | B15: =Funnel_Model!B17*Funnel_Model!B19*Funnel_Model!B25*100 -> 1.203125 | C15: =Funnel_Model!C17*Funnel_Model!C19*Funnel_Model!C25*100 -> 4.625 | D15: =Funnel_Model!D17*Funnel_Model!D19*Funnel_Model!D25*100 -> 14.625 | E15: Activation × repeat × share shifted; pilot target +4 to +6 pts
A16: Expected intention-to-treat lift in pilot (pts, net of 15% overlap) | B16: =B15*(1-Funnel_Model!B28) -> 1.0226563 | C16: =C15*(1-Funnel_Model!C28) -> 3.93125 | D16: =D15*(1-Funnel_Model!D28) -> 12.43125 | E16: As above × (1 − baseline overlap)
A19: Early indicator | B19: Target | E19: Status
A20: Activation within 30 days of exposure | B20: 15–25% | E20: Hypothesis, to validate in pilot
A21: Repeat: 2+ payments in each of months 2 and 3 | B21: 50% | E21: Hypothesis, to validate in pilot
A22: Settle & Pay payments per repeat merchant per month | B22: 6–8 | E22: Hypothesis, to validate in pilot
A23: Habit guard: share of payments made when no settlement gap existed | B23: ≥30% | E23: Hypothesis, to validate in pilot
A24: Incremental MTU per 1,000 exposed | B24: ≈65 (base) | E24: Hypothesis, to validate in pilot
A25: Wrong-payee payments per 1,000 | B25: Near zero (commitment) | E25: Hypothesis, to validate in pilot

Sheet Unit_Costs
A1: Unit costs: per incremental MTU and per ₹ of incremental GMV (base case)
A2: Every input is a labelled team assumption, not a Paytm figure. No cashback anywhere in the design.
A4: Item | B4: Value | C4: Note
A5: Field activation visit cost per exposed merchant (₹) | B5: 200 | C5: Assumption: Soundbox field force marginal cost (range ₹150–300)
A6: Visit cost, low (₹) | B6: 150 | C6: Assumption
A7: Visit cost, high (₹) | B7: 300 | C7: Assumption
A8: Float rate (annual) | B8: 0.11 | C8: Assumption: cost of releasing funds early
A9: Days settled early | B9: 1 | C9: Assumption
A10: Average vendor payment (₹) | B10: =Funnel_Model!C27 -> 2500 | C10: Link
A11: Free early settlement cost per payment (₹) | B11: =B10*B8/365*B9 -> 0.75342466 | C11: Ceiling: settling already-received funds mainly forgoes float income
A12: In-app prompts, notifications, WhatsApp (₹ per merchant) | B12: 0 | C12: Assumption: ≈₹0 marginal
A13: Pilot build: prompt, hand-off, fee waiver (₹) | B13: 5000000 | C13: Assumption: small build ≈₹0.5 crore, one-time
A14: Full in-app payer flow (₹) | B14: 50000000 | C14: Assumption: medium-large build ≈₹5 crore, only after the scale gate
A15: Exposed merchants | B15: =Funnel_Model!C11 -> 1196190.5 | C15: Link
A16: Incremental MTU | B16: =Funnel_Model!C22 -> 77799.107 | C16: Link
A17: Incremental payments a year | B17: =Funnel_Model!C26*12 -> 12522544 | C17: Run-rate × 12
A18: Incremental GMV a year (₹) | B18: =Funnel_Model!C29*12 -> 2.6610407e+10 | C18: Annual run-rate
A19: Field visit cost (₹) | B19: =B5*B15 -> 2.392381e+08 | C19: Visit cost × exposed
A20: Messaging cost (₹) | B20: =B12*B15 -> 0
A21: Free settlement cost a year (₹) | B21: =B11*B17 -> 9434793.6 | C21: Cost per payment × payments
A22: Total year-one cost, without build (₹) | B22: =B19+B20+B21 -> 2.4867289e+08
A23: Total year-one cost, with build (₹) | B23: =B22+B13+B14 -> 3.0367289e+08
A24: Cost per incremental MTU, without build (₹) | B24: =B22/B16 -> 3196.3463
A25: Cost per incremental MTU, with build (₹) | B25: =B23/B16 -> 3903.2953
A26: Cost per ₹ of incremental GMV, without build (₹) | B26: =B22/B18 -> 0.0093449489 | C26: Year-one cost ÷ annual run-rate GMV
A27: Cost per ₹ of incremental GMV, with build (₹) | B27: =B23/B18 -> 0.011411809
A28: Cost per ₹100 of incremental GMV, without build (₹) | B28: =B26*100 -> 0.93449489
A29: Cost per ₹100 of incremental GMV, with build (₹) | B29: =B27*100 -> 1.1411809
A30: Ramp-adjusted cost per ₹, with build (year-one GMV = 50% of run-rate) | B30: =B23/(B18*0.5) -> 0.022823619 | C30: Sensitivity on the denominator
A31: Pilot metric: visit cost per incremental MTU (₹200 × 1,000 ÷ MTU per 1,000) | B31: =B5*1000/Funnel_Model!C32 -> 3075.0751
A32: Cost per incremental MTU at visit cost ₹150, without build (₹) | B32: =(B6*B15+B20+B21)/B16 -> 2427.5775
A33: Cost per incremental MTU at visit cost ₹300, without build (₹) | B33: =(B7*B15+B20+B21)/B16 -> 4733.8838
A35: Durability once incentives stop
A36: No cashback in the design. The only economic element is free settlement when it funds a supplier payment: permanent product pricing, not a promotion.
A37: Durability test (a): repeat use after field-activation contact ends (days 31–90).
A38: Durability test (b): habit-guard share, i.e. usage when no settlement benefit applies.
A39: Durability test (c): optional sub-arm where free settlement reverts to standard pricing for days 61–90, to measure price sensitivity.

Sheet Sensitivity
A1: Sensitivity: the three assumptions that move the answer most (base case)
A2: PROJECTION. Each row recomputes the full chain with one driver changed. The model is multiplicative, so halving any of the three halves every output.
A3: Habit-guard target (bound for the gap-days floor) | E3: 0.3
A4: Scenario | B4: Settlement share | C4: Activation | D4: Repeat | E4: Shifted-payment factor | F4: Eligible | G4: Incremental MTU | H4: Annual GMV (₹ crore) | I4: vs base
A5: Base case | B5: =Funnel_Model!$C$7 -> 0.54761905 | C5: =Funnel_Model!$C$17 -> 0.23125 | D5: =Funnel_Model!$C$19 -> 0.5 | E5: 1 | F5: =Funnel_Model!$C$5*Funnel_Model!$C$6*B5*Funnel_Model!$C$8 -> 2990476.2 | G5: =F5*Funnel_Model!$C$10*C5*D5*Funnel_Model!$C$21 -> 77799.107 | H5: =F5*Funnel_Model!$C$10*C5*D5*Funnel_Model!$C$24*Funnel_Model!$C$25*Funnel_Model!$C$27*(1-Funnel_Model!$C$28)*E5*12/10^7 -> 2661.0407 | I5: =H5/$H$5 -> 1
A6: Settlement share halved | B6: =Funnel_Model!$C$7/2 -> 0.27380952 | C6: =Funnel_Model!$C$17 -> 0.23125 | D6: =Funnel_Model!$C$19 -> 0.5 | E6: 1 | F6: =Funnel_Model!$C$5*Funnel_Model!$C$6*B6*Funnel_Model!$C$8 -> 1495238.1 | G6: =F6*Funnel_Model!$C$10*C6*D6*Funnel_Model!$C$21 -> 38899.554 | H6: =F6*Funnel_Model!$C$10*C6*D6*Funnel_Model!$C$24*Funnel_Model!$C$25*Funnel_Model!$C$27*(1-Funnel_Model!$C$28)*E6*12/10^7 -> 1330.5203 | I6: =H6/$H$5 -> 0.5
A7: Activation halved | B7: =Funnel_Model!$C$7 -> 0.54761905 | C7: =Funnel_Model!$C$17/2 -> 0.115625 | D7: =Funnel_Model!$C$19 -> 0.5 | E7: 1 | F7: =Funnel_Model!$C$5*Funnel_Model!$C$6*B7*Funnel_Model!$C$8 -> 2990476.2 | G7: =F7*Funnel_Model!$C$10*C7*D7*Funnel_Model!$C$21 -> 38899.554 | H7: =F7*Funnel_Model!$C$10*C7*D7*Funnel_Model!$C$24*Funnel_Model!$C$25*Funnel_Model!$C$27*(1-Funnel_Model!$C$28)*E7*12/10^7 -> 1330.5203 | I7: =H7/$H$5 -> 0.5
A8: Repeat rate halved | B8: =Funnel_Model!$C$7 -> 0.54761905 | C8: =Funnel_Model!$C$17 -> 0.23125 | D8: =Funnel_Model!$C$19/2 -> 0.25 | E8: 1 | F8: =Funnel_Model!$C$5*Funnel_Model!$C$6*B8*Funnel_Model!$C$8 -> 2990476.2 | G8: =F8*Funnel_Model!$C$10*C8*D8*Funnel_Model!$C$21 -> 38899.554 | H8: =F8*Funnel_Model!$C$10*C8*D8*Funnel_Model!$C$24*Funnel_Model!$C$25*Funnel_Model!$C$27*(1-Funnel_Model!$C$28)*E8*12/10^7 -> 1330.5203 | I8: =H8/$H$5 -> 0.5
A9: Gap-days-only floor (base × (1 − habit guard)) | B9: =Funnel_Model!$C$7 -> 0.54761905 | C9: =Funnel_Model!$C$17 -> 0.23125 | D9: =Funnel_Model!$C$19 -> 0.5 | E9: =1-$E$3 -> 0.7 | F9: =Funnel_Model!$C$5*Funnel_Model!$C$6*B9*Funnel_Model!$C$8 -> 2990476.2 | G9: =F9*Funnel_Model!$C$10*C9*D9*Funnel_Model!$C$21 -> 77799.107 | H9: =F9*Funnel_Model!$C$10*C9*D9*Funnel_Model!$C$24*Funnel_Model!$C$25*Funnel_Model!$C$27*(1-Funnel_Model!$C$28)*E9*12/10^7 -> 1862.7285 | I9: =H9/$H$5 -> 0.7
A10: Share of payments shifted halved (GMV only) | B10: =Funnel_Model!$C$7 -> 0.54761905 | C10: =Funnel_Model!$C$17 -> 0.23125 | D10: =Funnel_Model!$C$19 -> 0.5 | E10: 0.5 | F10: =Funnel_Model!$C$5*Funnel_Model!$C$6*B10*Funnel_Model!$C$8 -> 2990476.2 | G10: =F10*Funnel_Model!$C$10*C10*D10*Funnel_Model!$C$21 -> 77799.107 | H10: =F10*Funnel_Model!$C$10*C10*D10*Funnel_Model!$C$24*Funnel_Model!$C$25*Funnel_Model!$C$27*(1-Funnel_Model!$C$28)*E10*12/10^7 -> 1330.5203 | I10: =H10/$H$5 -> 0.5
A12: Note: the gap-days-only floor assumes only payments made when a settlement gap exists move to Paytm; the pilot's habit-guard target (≥30% of payments with no gap) bounds the complement. MTU is unchanged in the floor and shift-share rows because the same merchants stay active.

Sheet Pilot_Design
A1: 90-day randomised pilot
A2: Design, metrics and decision gates
A4: Element | B4: Content
A5: Days 0–14 | B5: Pull settlement data; build the eligible list (next-day or separate-account settlement; vendor-payment pattern where visible); randomise by field-agent territory; pull a 60-day baseline from Paytm data; recruit the Account Aggregator share panel; ship the light build (S): collections-screen prompt, existing instant settlement with a fee waiver when it funds a supplier payment, hand-off to Paytm UPI with the supplier prefilled
A6: Days 15–90 | B6: Live for treatment. Arm A: Settle & Pay (light build) for all treatment merchants. Arm B: plus staff access for multi-payer shops. Field activation visits during days 15–30
A7: Cohort and control | B7: ≈3,000 treatment and ≈3,000 control merchants in two cities with dense Soundbox coverage; control gets no prompt and no fee waiver
A8: Baseline | B8: 60-day pre-period outgoing Paytm payments from Paytm data; Account Aggregator bank-statement panel of ≈300 consented merchants per arm for total business UPI
A9: Main metric | B9: Intention-to-treat change in Paytm's share of business UPI value, treatment vs control (difference-in-differences); target +4 to +6 pts
A10: Early indicators | B10: Activation within 30 days (15–25%); repeat: 2+ payments in each of months 2 and 3 (50%); 6–8 payments per repeat merchant a month; habit guard ≥30%; ≈65 incremental MTU per 1,000 exposed
A11: Durability | B11: (a) repeat after field contact ends, days 31–90; (b) habit-guard share; (c) optional sub-arm: free settlement reverts to standard pricing, days 61–90
A12: Safety | B12: Wrong-payee payments and support complaints per 1,000 payments: near zero (commitment)
A13: Scale if | B13: Activation ≥15%, repeat ≥40% and a statistically significant intention-to-treat share lift
A14: Revise if | B14: Activation fine but habit guard <15% (used only for settlement gaps)
A15: Stop if | B15: Activation <8%
A16: How to scale | B16: Build the full in-app payer flow (M/L); extend to all eligible merchants found through settlement data; Soundbox field-force waves by city; WhatsApp and in-app messaging; settlement-bank partnerships for current-account payers

Sheet Dependencies_Risks
A1: Dependency register and risk register
A2: Owners are proposed functions, not confirmed people.
A4: Mechanic / dependency | B4: What public sources indicate | C4: Still to confirm | D4: Owner | E4: Build effort
A5: Releasing today's collections early | B5: Paytm for Business already offers manual instant settlement; PhonePe offers Settle Now; RBI 2025 rules let the merchant agreement set settlement timing (S3, S6, S10) | C5: Credit speed to each partner bank; daily limits; whether merchant agreements need updating | D5: Settlement, treasury, compliance | E5: S
A6: Paying the supplier directly from collections | B6: Not allowed for most target merchants: third-party payouts need ₹40 lakh+ turnover and must go to the customer-facing payee (S10, S11) | C6: None: the design settles to the merchant's own account first; compliance to confirm the reading | D6: Compliance | E6: —
A7: Early release versus credit | B7: Settling only collections already received avoids pre-funding; summaries of 2025 rules don't classify pre-funded early settlement (S15) | C7: Formal compliance view; whether any pre-funding is ever needed | D7: Compliance, legal | E7: —
A8: One authorisation | B8: Settlement needs no UPI PIN; only the supplier payment does | C8: Settlement-to-credit time by bank; the waiting experience | D8: Payments engineering | E8: M
A9: Paying from Paytm for Business | B9: UPI works on current accounts (S14); the app lists no payer feature today (S3) | C9: Build the payer flow in-app, or keep the hand-off to Paytm UPI | D9: Engineering, partner banks | E9: S hand-off / M–L in-app
A10: Free settlement when it funds a supplier | B10: Competitor charges ₹1–3 a request, implying low unit cost (S6) | C10: Whether conditional free pricing is acceptable; cost at scale | D10: Compliance, pricing | E10: S
A11: Staff access (arm B) | B11: Not researched publicly | C11: Whether UPI delegated-payment limits fit vendor payments, or an approval workflow is needed | D11: Product, NPCI rules | E11: M
A12: Manual instant settlement for all device merchants (Phase 0) | B12: Feature exists in the app (S3); coverage across device merchants not public | C12: Is it available to every eligible device merchant today? | D12: Merchant product | E12: S
A13: Segment size | B13: Not public; Paytm help pages give different timings (S4, S5) | C13: Share of device merchants on next-day or separate-account settlement; share already using manual settlement | D13: Data team | E13: S
A16: Risk | B16: Signal | C16: Mitigation
A17: Most Paytm merchants already settle same day into the account they pay from | B17: Settlement data shows a small next-day / separate-account share | C17: Size it in days 0–14 before launch; shrink the target; lead with staff access for multi-payer shops
A18: Habit wins even with the step removed | B18: Low habit-guard share; activation without repeat | C18: Morning prompt on yesterday's collections; target Group 1 only; 'revise' gate if habit guard <15%
A19: PhonePe responds | B19: Adds supplier payment to Settle Now, or makes it free, for its own merchants | C19: Expected within months; it can't reach merchants whose collections Paytm handles; move first and lock in the habit
A20: The friction is already solved | B20: Many eligible merchants already use manual instant settlement | C20: Phase 0 measures it first; lead with one flow instead of two apps, and with staff access
A21: Compliance treats free conditional settlement or early release differently | B21: Compliance opinion before pilot | C21: Settle only already-received collections; fallback: standard-priced settlement plus hand-off
A22: Early-release cost | B22: ≈₹0.75 of float per ₹2,500 payment settled a day early (ceiling) | C22: Justify against measured retention and GMV lift; settle exact amounts only
A23: Trust in Paytm after 2024 | B23: Drop-off at the payment screen | C23: Show the source bank account on every payment screen; money never sits with Paytm
A24: Dataset limitations | B24: Synthetic data; 11 contradictory rows; repeated quotes | C24: All proxy rates replaced by Paytm data and pilot results before any scale decision

Sheet Sources
A1: Sources
A2: Access date for web sources: 9 Oct 2026. Verification status as of build.
A4: ID | B4: Source | C4: URL | D4: Used for | E4: Verification status
A5: S1 | B5: Paytm Q1 FY27 results release (Paytm investor relations blog) | C5: https://paytm.com/blog/investor-relations/paytm-q1-fy27-results-revenue-grows-28-to-2448-crore-highest-ever-quarterly-ebitda-at-203-crore/ | D5: 1.57 crore merchants paying for Paytm payment devices (quarter to June 2026) | E5: Verified via web search, 9 Oct 2026
A6: S2 | B6: NPCI UPI app-wise statistics, August 2026 (reported by StartupTalky) | C6: https://startuptalky.com/upi-transactions-september-2026/ | D6: App-wise UPI volume share: Paytm 8.03%, PhonePe 45.64%, Google Pay 32.26% (value: 6.87% / 47.82% / 33.78%) | E6: Secondary report of NPCI data; confirm on npci.org.in before submission
A7: S3 | B7: Paytm for Business app listing (App Store copy; Google Play com.paytm.business) | C7: https://apps.apple.com/in/app/id1351301966 ; https://play.google.com/store/apps/details?id=com.paytm.business | D7: 'Instant Bank Settlements: select the frequency of the settlements or manually settle'; acceptance, statements, settlements, loans; no vendor-payment feature listed | E7: Listing text verified via App Store / APK mirror copy; Play page not reachable from build environment
A8: S4 | B8: Paytm for Business support: how Paytm transfers payments to your bank | C8: https://paytm.business/support/how-does-paytm-transfer-payments-i-have-received-to-my-bank-account | D8: 'Usually settled to your bank within T+1 days ... may get extended due to bank holidays' | E8: Verified via web search snippet, 9 Oct 2026
A9: S5 | B9: Paytm Payments developer docs: settlement processing | C9: https://www.paytmpayments.com/docs/settlement-processing-in-paytm | D9: 'Typically occurs within a few business hours or at the T+N cycle' | E9: Verified via web search snippet, 9 Oct 2026
A10: S6 | B10: PhonePe merchant help: charges for a Settle Now request | C10: https://cms.phonepe.com/en/mx/merchant-help/settlements/know-more-about-settlements/about-early-settlements/are-there-any-charges-raising-early-settlement-request | D10: ₹1 (₹1–999), ₹2 (₹1,000–24,999), ₹3 (₹25,000–5 lakh) per request, incl. GST; deducted from next settlement | E10: Verified via web search, 9 Oct 2026
A11: S7 | B11: PhonePe merchant help: why can't I place a Settle Now request | C11: https://cms.phonepe.com/en/mx/merchant-help/on-demand-or-early-settlement/why-am-i-not-able-place-settle-now-request | D11: One request an hour until 11 pm; only selected merchants are eligible | E11: Verified via web search, 9 Oct 2026
A12: S8 | B12: PhonePe merchant help: settlement time | C12: https://cms.phonepe.com/en/mx/merchant-help/settlements/can-i-change-settlement-time/ | D12: Merchants settled by 8 am the next day | E12: Cited in team solution document; not re-verified
A13: S9 | B13: RBI press release: Regulation of Payment Aggregators Directions, 2025 (15 Sep 2025) | C13: https://website.rbi.org.in/web/rbi/-/press-releases/rbi-issues-the-reserve-bank-of-india-regulation-of-payment-aggregators-directions-2025 | D13: Directions issued and effective; supersede 2020/2021 PA-PG guidelines | E13: Verified via web search; payout clause read from legal summaries, primary text to be confirmed
A14: S10 | B14: Vinod Kothari Consultants: key highlights of PA Directions 2025 | C14: https://vinodkothari.com/wp-content/uploads/2025/09/Key-Highlights-of-PA-2025-2.pdf | D14: Third-party payouts only for merchants with turnover above ₹40 lakh, to the payee in the underlying transaction; settlement timeline mutually agreed (T+1 suggestion removed) | E14: Legal summary, verified via web search, 9 Oct 2026
A15: S11 | B15: Cyril Amarchand Mangaldas client alert on PA Directions 2025 | C15: https://www.cyrilshroff.com/wp-content/uploads/2025/10/Client-Alert-RBI-Introduces-Consolidated-Framework-for-Payment-Aggregators-3.pdf | D15: Payment to a third party on merchant directions allowed only for certain merchants | E15: Legal summary, verified via web search, 9 Oct 2026
... A21: S17 | B21: Paytitude_ExecSummary.pdf (Round 1 submission, 25 Sep 2026) | C21: Internal file | D21: Round 1 segment, solution, impact and pilot, for the change log | E21: Read in full

Sheet Change_Log_R1_R2
A1: What changed since Round 1, and why
A2: Round 1 column verified against Paytitude_ExecSummary.pdf (25 Sep 2026). Track B kept.
A4: Area | B4: Round 1 | C4: Round 2 | D4: Why
A5: Problem framing | B5: 'Paytm owns the counter, not the payout'; the 0.4% MDR from 15 Oct 2026 would push supplier payments to NEFT and cash | C5: Paytm owns the moment money arrives, not the moment it is spent; no MDR argument | D5: The fee is not why merchants choose an app, and the MDR argument was legally fragile
A6: Segment | B6: Paytm QR / Soundbox merchants collecting over ₹1 lakh a month on UPI (≈24 lakh), starting in Andheri trade clusters | C6: Same track and base (Paytm-collecting merchants who pay suppliers by UPI), re-cut by behaviour: next-day or separate-account settlement, weekly vendor UPI, a stated friction | D6: That is where removing a step gives a reason to switch; settlement profile, not size, separated interested from indifferent merchants in the stress-test data
A7: Solution | B7: Supplier Pay: four layers (pay from settlement account; invoice-matched receipts and distributor ledger; due-date payments with partner credit; Supplier Khata) | C7: Settle & Pay: one flow that settles already-received collections to the merchant's own account, then pays the supplier by UPI; free when it funds a supplier payment | D7: Settlement plus payment in one flow is the Paytm-specific edge
A8: Credit | B8: 30-day partner-lender credit; break-even at ≈18% supplier credit cost | C8: Dropped | D8: No credit need in the evidence; economics were thin
A9: Ledger and invoices | B9: Supplier Khata, GST and Tally export; invoice-matched receipts | C9: Dropped from the MVP | D9: Billing software already owns this
A10: Impact estimate | B10: ≈₹27,000 crore a year extra GMV (24 lakh × ₹1 lakh × +11 pts, less 13% leakage); +1–2 lakh new merchant payers | C10: Staged funnel: base ₹2,660 crore annual run-rate (₹240–19,400 crore); ≈78,000 incremental MTU | D10: The ₹27,000 crore rested on simulated data and planned supplier payments
A11: Pilot | B11: 500 Andheri merchants vs control, before Diwali; month-12 target 30% outflow share | C11: 90-day pilot randomised by field-agent territory, ≈3,000 vs 3,000 in two cities; intention-to-treat share target +4 to +6 pts; scale / revise / stop gates | D11: To prove incrementality before scale
A12: Evidence base | B12: Summary cited 'VOC dataset, n=50 Andheri merchants' | C12: Segment proxies come from a 50-row dataset disclosed as synthetic (hypothesis stress-testing only); ≥20-user validation added (results pending) | D12: Keeps hypothesis and evidence visibly separate
